<?xml version="1.0" encoding="UTF-8" standalone="yes"?>
<objectsMobile>
    <asignado>Noelia</asignado>
    <descripcion>Aplicacion Android - Realizar VC - Gmail</descripcion>
    <estado>Falla</estado>
    <imgFalla>C:\imageRepository\FALLA_S_Home_02_20191007085053.png</imgFalla>
    <modulo>Socio</modulo>
    <nombreDeLaPrueba>S_Home_02</nombreDeLaPrueba>
    <pasos>
        <entry>
            <key>01_Se verifica que sean visibles los elementos de la home</key>
            <value>Falla</value>
        </entry>
    </pasos>
    <prioridad>Alta</prioridad>
    <referencia>Referencia</referencia>
    <sprint>Ciclo 0</sprint>
    <tiempoFinal>285</tiempoFinal>
    <tiempoInicio>1570492247</tiempoInicio>
    <tipoDePrueba>Regresión</tipoDePrueba>
    <usuario>
        <email>cmotest5@cmo.com</email>
        <password>Cmotest5!</password>
    </usuario>
    <version>4.2.0</version>
</objectsMobile>
